pydantic_settings_external/__init__.py
pydantic_settings_external/exceptions.py
pydantic_settings_external/types.py
pydantic_settings_external/utils.py
pydantic_settings_external/version.py
pydantic_settings_external/pydantic/__init__.py
pydantic_settings_external/pydantic/v1.py
pydantic_settings_external/pydantic/v2.py
pydantic_settings_external-0.1.0.dist-info/LICENSE
pydantic_settings_external-0.1.0.dist-info/METADATA
pydantic_settings_external-0.1.0.dist-info/WHEEL
pydantic_settings_external-0.1.0.dist-info/top_level.txt
pydantic_settings_external-0.1.0.dist-info/RECORD
