Metadata-Version: 2.1
Name: pydantic-settings-external
Version: 0.1.0
Summary: PyDantic Settings External is a library that extends PyDantic Settings to support various types of external configuration providers, such as GCP Secret Manager and AWS Secrets Manager. PyDantic Settings External has been developed using a clear abstraction, allowing for easy extension to external configurations not yet incorporated into the library by the community.
Author-email: Ali Aliyev <ali@aliev.me>
Project-URL: Homepage, https://github.com/aliev/pydantic-settings-external
Project-URL: Bug Tracker, https://github.com/aliev/pydantic-settings-external/issues
Keywords: pydantic,pydantic-settings
Classifier: Development Status :: 5 - Production/Stable
Classifier: Intended Audience :: Developers
Classifier: Programming Language :: Python
Classifier: License :: OSI Approved :: MIT License
Classifier: Natural Language :: English
Classifier: Operating System :: OS Independent
Classifier: Programming Language :: Python
Classifier: Programming Language :: Python :: 3
Classifier: Programming Language :: Python :: 3.8
Classifier: Programming Language :: Python :: 3.9
Classifier: Programming Language :: Python :: 3.10
Classifier: Framework :: AsyncIO
Classifier: Topic :: Software Development :: Libraries :: Python Modules
Classifier: Topic :: Utilities
Requires-Python: >=3.8
License-File: LICENSE
Provides-Extra: dev
Requires-Dist: pre-commit ; extra == 'dev'
Requires-Dist: wheel ; extra == 'dev'
Requires-Dist: twine ; extra == 'dev'
Requires-Dist: build ; extra == 'dev'
Requires-Dist: pytest ; extra == 'dev'
Requires-Dist: pytest-cov ; extra == 'dev'
